math_package_xgqfrms/__init__.py
math_package_xgqfrms/math.py
math_package_xgqfrms-0.0.2.dist-info/METADATA
math_package_xgqfrms-0.0.2.dist-info/WHEEL
math_package_xgqfrms-0.0.2.dist-info/licenses/LICENSE
math_package_xgqfrms-0.0.2.dist-info/RECORD
