Metadata-Version: 2.1
Name: math_package_xgqfrms
Version: 0.0.2
Summary: A math package of python 3. 🐍
Project-URL: PyPi 🐍, https://pypi.org/project/math-package-xgqfrms/
Project-URL: Website 🌏, https://math_package_project.xgqfrms.xyz/
Project-URL: GitHub 🐙, https://github.com/xgqfrms/math_package_project
Project-URL: Issues ❓, https://github.com/xgqfrms/math_package_project/issues
Project-URL: Wiki 🗂️, https://github.com/xgqfrms/math_package_project/issues
Author-email: xgqfrms <xgqfrms@xgqfrms.xyz>
License-Expression: MIT
License-File: LICENSE
Keywords: linux,math,package,python,xgqfrms
Classifier: Intended Audience :: Developers
Classifier: License :: OSI Approved :: MIT License
Classifier: Operating System :: OS Independent
Classifier: Programming Language :: Python :: 3
Classifier: Topic :: Software Development :: Libraries :: Python Modules
Requires-Python: >=3.7
